wasenderapi/__init__.py
wasenderapi/_version.py
wasenderapi/async_client.py
wasenderapi/channel.py
wasenderapi/contacts.py
wasenderapi/errors.py
wasenderapi/groups.py
wasenderapi/models.py
wasenderapi/sessions.py
wasenderapi/sync_client.py
wasenderapi/webhook.py
wasenderapi-0.3.4.dist-info/METADATA
wasenderapi-0.3.4.dist-info/WHEEL
wasenderapi-0.3.4.dist-info/licenses/LICENSE
wasenderapi-0.3.4.dist-info/RECORD
