Metadata-Version: 2.4
Name: wasenderapi
Version: 0.3.4
Summary: The official Python SDK for the Wasender API, allowing you to programmatically send WhatsApp messages, manage contacts, groups, sessions, and handle webhooks.
Project-URL: Homepage, https://github.com/YonkoSam/wasenderapi-python
Project-URL: Documentation, https://github.com/YonkoSam/wasenderapi-python/tree/main/docs
Project-URL: Repository, https://github.com/YonkoSam/wasenderapi-python
Project-URL: Bug Tracker, https://github.com/YonkoSam/wasenderapi-python/issues
Author-email: YonkoSam <absamlani@gmail.com>
License-File: LICENSE
Keywords: api,chatbot,messaging,sdk,wasender,whatsapp
Classifier: Development Status :: 4 - Beta
Classifier: Intended Audience :: Developers
Classifier: License :: OSI Approved :: MIT License
Classifier: Operating System :: OS Independent
Classifier: Programming Language :: Python :: 3
Classifier: Programming Language :: Python :: 3.8
Classifier: Programming Language :: Python :: 3.9
Classifier: Programming Language :: Python :: 3.10
Classifier: Programming Language :: Python :: 3.11
Classifier: Programming Language :: Python :: 3.12
Classifier: Topic :: Communications :: Chat
Classifier: Topic :: Software Development :: Libraries :: Python Modules
Requires-Python: >=3.8
Requires-Dist: httpx<0.29.0,>=0.25.0
Requires-Dist: pydantic<3.0.0,>=2.5.0
Requires-Dist: requests<3.0.0,>=2.31.0
Provides-Extra: dev
Requires-Dist: flake8<7.0.0,>=6.0.0; extra == 'dev'
Requires-Dist: mypy<2.0.0,>=1.0.0; extra == 'dev'
Requires-Dist: pre-commit<4.0.0,>=3.0.0; extra == 'dev'
Requires-Dist: pytest-asyncio<0.24.0,>=0.20.0; extra == 'dev'
Requires-Dist: pytest-cov<5.0.0,>=4.1.0; extra == 'dev'
Requires-Dist: pytest-mock<4.0.0,>=3.12.0; extra == 'dev'
Requires-Dist: pytest<8.0.0,>=7.4.0; extra == 'dev'
Requires-Dist: respx<0.21.0,>=0.20.0; extra == 'dev'
Requires-Dist: ruff<0.2.0,>=0.1.0; extra == 'dev'
